LICENSE.txt
MANIFEST.in
README.md
pyproject.toml
requirements.txt
setup.cfg
setup.py
elearning_grading/__about__.py
elearning_grading/__init__.py
elearning_grading.egg-info/PKG-INFO
elearning_grading.egg-info/SOURCES.txt
elearning_grading.egg-info/dependency_links.txt
elearning_grading.egg-info/entry_points.txt
elearning_grading.egg-info/not-zip-safe
elearning_grading.egg-info/requires.txt
elearning_grading.egg-info/top_level.txt
elearning_grading/generate/__init__.py
elearning_grading/generate/generate.py
elearning_grading/organize/__init__.py
elearning_grading/organize/organize.py
elearning_grading/organize/project_members.py
elearning_grading/organize/project_organize.py
elearning_grading/utilities/__init__.py
elearning_grading/utilities/el_utils.py