Metadata-Version: 2.1
Name: elearning-grading
Version: 0.2.2
Summary: Python utilities to help Teaching Assistants grade assignments with eLearning
Home-page: https://github.com/Supermaxman/elearning-grading
Author: Maxwell Weinzierl
Author-email: maxwell.weinzierl@utdallas.edu
License: Apache-2.0
Download-URL: https://github.com/Supermaxman/elearning-grading
Project-URL: Bug Tracker, https://github.com/Supermaxman/elearning-grading/issues
Project-URL: Source Code, https://github.com/Supermaxman/elearning-grading
Keywords: grading,elearning,education,teaching
Platform: UNKNOWN
Classifier: Environment :: Console
Classifier: Natural Language :: English
Classifier: Development Status :: 3 - Alpha
Classifier: Intended Audience :: Education
Classifier: Topic :: Education
Classifier: License :: OSI Approved :: Apache Software License
Classifier: Operating System :: OS Independent
Classifier: Programming Language :: Python :: 3
Classifier: Programming Language :: Python :: 3.6
Classifier: Programming Language :: Python :: 3.7
Classifier: Programming Language :: Python :: 3.8
Classifier: Programming Language :: Python :: 3.9
Requires-Python: >=3.6
License-File: LICENSE.txt
